<?xml version="1.0"?>
<save_state>
	<input />
	<window />
	<textures />
	<audio />
	<scene />
	<renderer>
		<camera x="213" y="158" />
	</renderer>
	<player>
		<position x="444" y="212" />
		<partners>
			<partner_1 x="404" y="212" />
			<partner_2 x="364" y="212" />
			<partner_3 x="324" y="212" />
		</partners>
		<coins count="0" />
		<lives num_respawns="3" />
	</player>
	<scene_manager>
		<level lvl="1" />
	</scene_manager>
	<entities />
	<entity_manager>
		<score value="0" />
		<time value="4090" />
		<entities>
			<entity type="4" x="0" y="0" state="0" />
		</entities>
	</entity_manager>
</save_state>
