<?xml version="1.0"?>
<save_state>
	<input />
	<window />
	<textures />
	<audio />
	<scene />
	<renderer>
		<camera x="70" y="90" />
	</renderer>
	<player>
		<data x="570" y="270" direction="3" level="1" exp="0" health="8" />
		<coins count="0" />
		<path />
		<partners>
			<partner x="530" y="270" breadcrumb="0" direction="1" level="1" exp="0" />
			<partner x="490" y="270" breadcrumb="0" direction="1" level="1" exp="0" />
			<partner x="450" y="270" breadcrumb="0" direction="1" level="1" exp="0" />
		</partners>
	</player>
	<scene_manager>
		<level lvl="1" />
	</scene_manager>
	<entities />
	<entity_manager>
		<score value="0" />
		<time value="0" />
		<entities>
			<entity type="13" x="-2" y="-2" id="0" level="0" state="0" move="true" />
			<entity type="1" x="26" y="14" id="1" level="1" state="0" move="true" />
			<entity type="2" x="24" y="8" id="2" level="1" state="0" move="false" />
			<entity type="3" x="16" y="5" id="3" level="2" state="0" move="false" />
			<entity type="14" x="21" y="6" id="2" level="0" state="0" move="false" />
		</entities>
	</entity_manager>
</save_state>
